README.md
setup.py
ipdb/__init__.py
ipdb/asn.py
ipdb/base_station.py
ipdb/city.py
ipdb/database.py
ipdb/district.py
ipdb/exceptions.py
ipdb/idc.py
ipdb/util.py
ipip_ipdb.egg-info/PKG-INFO
ipip_ipdb.egg-info/SOURCES.txt
ipip_ipdb.egg-info/dependency_links.txt
ipip_ipdb.egg-info/top_level.txt