Metadata-Version: 1.1
Name: ipip-ipdb
Version: 1.6.0
Summary: IPIP.net officially supported IP database ipdb format parsing library
Home-page: https://github.com/ipipdotnet/ipdb-python
Author: frk
Author-email: frk@ipip.net
License: Apache License Version 2.0
Platform: all
Classifier: Development Status :: 4 - Beta
Classifier: Operating System :: OS Independent
Classifier: Intended Audience :: Developers
Classifier: Programming Language :: Python
Classifier: Programming Language :: Python :: Implementation
Classifier: Programming Language :: Python :: 2
Classifier: Programming Language :: Python :: 2.7
Classifier: Programming Language :: Python :: 3
Classifier: Programming Language :: Python :: 3.4
Classifier: Programming Language :: Python :: 3.5
Classifier: Programming Language :: Python :: 3.6
Classifier: Topic :: Software Development :: Libraries
